papilon/__init__.py
papilon/causal.py
papilon/energy.py
papilon/entropy.py
papilon/optimizer.py
papilon/relationships.py
papilon/simulation.py
papilon/states.py
papilon-0.2.0.dist-info/licenses/LICENSE
papilon-0.2.0.dist-info/METADATA
papilon-0.2.0.dist-info/WHEEL
papilon-0.2.0.dist-info/top_level.txt
papilon-0.2.0.dist-info/RECORD
