Metadata-Version: 2.4
Name: papilon
Version: 0.2.0
Summary: Papilon: A Statistical Mechanics Framework for Causal Data Simulation
Author-email: Brian Curry <0.1.vectorlabs@gmail.com>
License: MIT
Requires-Python: >=3.8
License-File: LICENSE
Requires-Dist: numpy
Requires-Dist: pandas
Requires-Dist: scikit-learn
Requires-Dist: seaborn
Requires-Dist: matplotlib
Requires-Dist: networkx
Dynamic: license-file
